bartide/__init__.py
bartide/batch_analyzer.py
bartide/config.py
bartide/paired_extractor.py
bartide/sequence_corrector.py
bartide/utils.py
bartide-0.3.2.dist-info/LICENSE
bartide-0.3.2.dist-info/METADATA
bartide-0.3.2.dist-info/WHEEL
bartide-0.3.2.dist-info/top_level.txt
bartide-0.3.2.dist-info/RECORD
