Metadata-Version: 2.1
Name: bartide
Version: 0.3.2
Summary: A Python package to extract, correct and analyze nucleotide barcodes from sequenced reads.
Home-page: https://github.com/parashardhapola/bartide
Author: Parashar Dhapola
Author-email: parashar.dhapola@gmail.com
Keywords: Text Mining,Barcode,nucleotide,sequencing,deduplicate
Classifier: Development Status :: 4 - Beta
Classifier: Programming Language :: Python :: 3
Classifier: Programming Language :: Python :: 3.9
Classifier: License :: OSI Approved :: MIT License
Classifier: Intended Audience :: Developers
Classifier: Intended Audience :: Science/Research
Classifier: Intended Audience :: Education
Classifier: Topic :: Scientific/Engineering :: Bio-Informatics
Classifier: Operating System :: OS Independent
License-File: LICENSE
Requires-Dist: numpy
Requires-Dist: matplotlib
Requires-Dist: loguru
Requires-Dist: editdistance
Requires-Dist: tqdm
Requires-Dist: pandas
Requires-Dist: joblib
Requires-Dist: seaborn
Requires-Dist: upsetplot
Provides-Extra: dev
Requires-Dist: pytest ; extra == 'dev'
Requires-Dist: pytest-pep8 ; extra == 'dev'
Requires-Dist: pytest-cov ; extra == 'dev'
Requires-Dist: black ; extra == 'dev'
